[
  {
    "source": "security-matrix",
    "stack": "AWS GenAI IDP Accelerator - Sample BDA lending package project",
    "resourceType": "IAM Role",
    "resourceName": "LambdaExecutionRole",
    "issue": "Role policy contains wildcard (*) resource for multiple bedrock actions, violating principle of least privilege",
    "priority": "High",
    "status": "Open"
  },
  {
    "source": "security-matrix",
    "stack": "AWS GenAI IDP Accelerator - Sample BDA lending package project",
    "resourceType": "Lambda Function",
    "resourceName": "BDAProjectLambda",
    "issue": "Lambda function does not have VPC configuration, exposing it to potential network-level threats",
    "priority": "Medium",
    "status": "Open"
  },
  {
    "source": "security-matrix",
    "stack": "AWS GenAI IDP Accelerator - Sample BDA lending package project",
    "resourceType": "Lambda Function",
    "resourceName": "BDAProjectLambda",
    "issue": "Lambda function doesn't have X-Ray tracing enabled for monitoring and debugging",
    "priority": "High",
    "status": "Open"
  },
  {
    "source": "security-matrix",
    "stack": "AWS GenAI IDP Accelerator - Sample BDA lending package project",
    "resourceType": "Lambda Function",
    "resourceName": "BDAProjectLambda",
    "issue": "Lambda function doesn't implement a dead-letter queue for handling failed executions",
    "priority": "Medium",
    "status": "Open"
  },
  {
    "source": "security-matrix",
    "stack": "AWS GenAI IDP Accelerator - Sample BDA lending package project",
    "resourceType": "Lambda Function",
    "resourceName": "BDAProjectLambda",
    "issue": "Lambda function doesn't have ReservedConcurrentExecutions configured to prevent service disruptions",
    "priority": "Medium",
    "status": "Open"
  },
  {
    "source": "security-matrix",
    "stack": "AWS GenAI IDP Accelerator - Sample BDA lending package project",
    "resourceType": "General",
    "resourceName": "All Resources",
    "issue": "No resource tagging strategy implemented for cost allocation and resource management",
    "priority": "High",
    "status": "Open"
  }
]